Terminalia/Terminalia.py
Terminalia/__init__.py
Terminalia-0.0.4.dist-info/METADATA
Terminalia-0.0.4.dist-info/WHEEL
Terminalia-0.0.4.dist-info/top_level.txt
Terminalia-0.0.4.dist-info/RECORD
